native_engine.cpython-39-darwin.so
pants/__init__.py
pants/__main__.py
pants/dummy.c
pants/py.typed
pants/version.py
pants/_version/VERSION
pants/_version/__init__.py
pants/backend/__init__.py
pants/backend/adhoc/__init__.py
pants/backend/adhoc/adhoc_tool.py
pants/backend/adhoc/run_system_binary.py
pants/backend/adhoc/target_types.py
pants/backend/awslambda/__init__.py
pants/backend/awslambda/python/__init__.py
pants/backend/awslambda/python/register.py
pants/backend/awslambda/python/rules.py
pants/backend/awslambda/python/target_types.py
pants/backend/build_files/__init__.py
pants/backend/build_files/utils.py
pants/backend/build_files/fix/__init__.py
pants/backend/build_files/fix/base.py
pants/backend/build_files/fix/deprecations/__init__.py
pants/backend/build_files/fix/deprecations/base.py
pants/backend/build_files/fix/deprecations/register.py
pants/backend/build_files/fix/deprecations/renamed_fields_rules.py
pants/backend/build_files/fix/deprecations/renamed_targets_rules.py
pants/backend/build_files/fix/deprecations/subsystem.py
pants/backend/build_files/fmt/__init__.py
pants/backend/build_files/fmt/base.py
pants/backend/build_files/fmt/black/__init__.py
pants/backend/build_files/fmt/black/register.py
pants/backend/build_files/fmt/buildifier/__init__.py
pants/backend/build_files/fmt/buildifier/register.py
pants/backend/build_files/fmt/buildifier/rules.py
pants/backend/build_files/fmt/buildifier/subsystem.py
pants/backend/build_files/fmt/yapf/__init__.py
pants/backend/build_files/fmt/yapf/register.py
pants/backend/cc/__init__.py
pants/backend/cc/target_types.py
pants/backend/cc/dependency_inference/__init__.py
pants/backend/cc/dependency_inference/rules.py
pants/backend/cc/goals/__init__.py
pants/backend/cc/goals/tailor.py
pants/backend/cc/lint/__init__.py
pants/backend/cc/lint/clangformat/__init__.py
pants/backend/cc/lint/clangformat/clangformat.lock
pants/backend/cc/lint/clangformat/rules.py
pantsbuild.pants-2.17.1.dist-info/METADATA
pantsbuild.pants-2.17.1.dist-info/WHEEL
pantsbuild.pants-2.17.1.dist-info/entry_points.txt
pantsbuild.pants-2.17.1.dist-info/namespace_packages.txt
pantsbuild.pants-2.17.1.dist-info/top_level.txt
pantsbuild.pants-2.17.1.dist-info/zip-safe
pantsbuild.pants-2.17.1.dist-info/RECORD
