Metadata-Version: 2.1
Name: pantsbuild.pants
Version: 2.17.1
Summary: The ergonomic and hermetic software build system for Python, Java, Scala, Go, and Shell. Pants lets you fearlessly scale up your codebase.
Home-page: https://github.com/pantsbuild/pants
License: Apache License, Version 2.0
Project-URL: Documentation, https://www.pantsbuild.org/
Project-URL: Source, https://github.com/pantsbuild/pants
Project-URL: Tracker, https://github.com/pantsbuild/pants/issues
Project-URL: Changelog, https://www.pantsbuild.org/docs/changelog
Project-URL: Twitter, https://twitter.com/pantsbuild
Project-URL: Slack, https://www.pantsbuild.org/docs/getting-help
Project-URL: YouTube, https://www.youtube.com/channel/UCCcfCbDqtqlCkFEuENsHlbQ
Project-URL: Mailing lists, https://www.pantsbuild.org/docs/getting-help
Classifier: Intended Audience :: Developers
Classifier: License :: OSI Approved :: Apache Software License
Classifier: Operating System :: MacOS :: MacOS X
Classifier: Operating System :: POSIX :: Linux
Classifier: Programming Language :: Python
Classifier: Topic :: Software Development :: Build Tools
Requires-Python: >=3.7,<3.10
Requires-Dist: PyYAML (<7.0,>=6.0)
Requires-Dist: ansicolors (==1.1.8)
Requires-Dist: chevron (==0.14.0)
Requires-Dist: fasteners (==0.16.3)
Requires-Dist: ijson (==3.1.4)
Requires-Dist: importlib-resources (==5.0.*)
Requires-Dist: node-semver (==0.9.0)
Requires-Dist: packaging (==21.3)
Requires-Dist: pex (==2.1.137)
Requires-Dist: psutil (==5.9.0)
Requires-Dist: python-lsp-jsonrpc (==1.0.0)
Requires-Dist: setproctitle (==1.3.2)
Requires-Dist: setuptools (<64.0,>=63.1.0)
Requires-Dist: toml (==0.10.2)
Requires-Dist: types-PyYAML (==6.0.3)
Requires-Dist: types-setuptools (==62.6.1)
Requires-Dist: types-toml (==0.10.8)
Requires-Dist: typing-extensions (==4.3.0)
